{
    "timestamp": "2026-06-24 16:35:08",
    "vehicle_twin": {
        "vehicle_id": "vehicle_10",
        "speed": 21.47,
        "battery": 28.95,
        "cpu_usage": 39.83,
        "task_queue": 8,
        "health_status": "WARNING"
    },
    "road_twin": {
        "intersection_id": "advanced_sumo_junction_01",
        "traffic_density": "HIGH",
        "signal_state": "EW_GREEN",
        "active_vehicles": 40,
        "average_speed": 10.9,
        "congestion_level": "CONGESTED"
    },
    "edge_twin": {
        "edge_server_id": "edge_node_01",
        "cpu_load": 23.53,
        "memory_usage": 85.11,
        "active_tasks": 79,
        "latency_ms": 21.95,
        "status": "DEGRADED"
    },
    "cloud_twin": {
        "cloud_region": "cloud_region_01",
        "cpu_load": 69.25,
        "memory_usage": 84.67,
        "active_tasks": 39,
        "latency_ms": 138.18,
        "status": "NORMAL"
    }
}